pyvcham/__init__.py
pyvcham/constants.py
pyvcham/couplingfunct.py
pyvcham/diabfunct.py
pyvcham/gui.py
pyvcham/logging_config.py
pyvcham/lvc.py
pyvcham/symm_vcham.py
pyvcham/utils.py
pyvcham/vcham_system.py
pyvcham-1.0.0.dist-info/licenses/LICENSE.md
pyvcham-1.0.0.dist-info/METADATA
pyvcham-1.0.0.dist-info/WHEEL
pyvcham-1.0.0.dist-info/top_level.txt
pyvcham-1.0.0.dist-info/RECORD
