Metadata-Version: 2.4
Name: pyvcham
Version: 1.0.0
Summary: A scientific module for vibrational coupling Hamiltonian analysis.
Author-email: Emilio Rodríguez Cuenca <emilioerc@gmail.com>
Maintainer-email: Emilio Rodríguez Cuenca <emilioerc@gmail.com>
License: MIT License
Project-URL: Homepage, https://gitlab.com/tc-heidelberg/pyvcham
Keywords: vibrational coupling,quantum chemistry,spectroscopy,Jahn-Teller
Classifier: Programming Language :: Python :: 3
Classifier: Programming Language :: Python :: 3.10
Classifier: Programming Language :: Python :: 3.11
Classifier: Programming Language :: Python :: 3.12
Classifier: License :: OSI Approved :: MIT License
Classifier: Operating System :: OS Independent
Classifier: Intended Audience :: Science/Research
Classifier: Topic :: Scientific/Engineering :: Chemistry
Classifier: Topic :: Scientific/Engineering :: Physics
Requires-Python: <3.13,>=3.10
License-File: LICENSE.md
Requires-Dist: numpy>=1.26.0
Requires-Dist: tensorflow>=2.17.0
Requires-Dist: matplotlib>=3.5
Provides-Extra: dev
Requires-Dist: pytest>=7.0; extra == "dev"
Requires-Dist: pytest-cov>=3.0; extra == "dev"
Requires-Dist: ruff>=0.0.270; extra == "dev"
Requires-Dist: mypy>=0.900; extra == "dev"
Requires-Dist: black>=23.0; extra == "dev"
Requires-Dist: isort>=5.0; extra == "dev"
Requires-Dist: pre-commit>=3.0; extra == "dev"
Requires-Dist: sphinx>=5.0; extra == "dev"
Requires-Dist: sphinx_rtd_theme>=1.0; extra == "dev"
Requires-Dist: numpydoc>=1.0; extra == "dev"
Provides-Extra: doc
Requires-Dist: sphinx>=5.0; extra == "doc"
Requires-Dist: sphinx_rtd_theme>=1.0; extra == "doc"
Requires-Dist: numpydoc>=1.0; extra == "doc"
Dynamic: license-file
